LICENSE
MANIFEST.in
README.md
setup.cfg
setup.py
docassemble/__init__.py
docassemble.LAWVMediaRelease.egg-info/PKG-INFO
docassemble.LAWVMediaRelease.egg-info/SOURCES.txt
docassemble.LAWVMediaRelease.egg-info/dependency_links.txt
docassemble.LAWVMediaRelease.egg-info/namespace_packages.txt
docassemble.LAWVMediaRelease.egg-info/not-zip-safe
docassemble.LAWVMediaRelease.egg-info/top_level.txt
docassemble/LAWVMediaRelease/__init__.py
docassemble/LAWVMediaRelease/data/questions/lawv_media_release.yml
docassemble/LAWVMediaRelease/data/sources/README.md
docassemble/LAWVMediaRelease/data/static/LAWV_Client_Story_Release_flat.pdf
docassemble/LAWVMediaRelease/data/static/LAWV_Media_Release_flat.pdf
docassemble/LAWVMediaRelease/data/static/README.md
docassemble/LAWVMediaRelease/data/templates/LAWV_Client_Story_Release.pdf
docassemble/LAWVMediaRelease/data/templates/LAWV_Media_Release.pdf
docassemble/LAWVMediaRelease/data/templates/README.md